OptiMultiPy/__init__.py
OptiMultiPy/versao_final.py
OptiMultiPy-0.0.1.3.dist-info/METADATA
OptiMultiPy-0.0.1.3.dist-info/WHEEL
OptiMultiPy-0.0.1.3.dist-info/licence
OptiMultiPy-0.0.1.3.dist-info/top_level.txt
OptiMultiPy-0.0.1.3.dist-info/RECORD
