Metadata-Version: 2.1
Name: OptiMultiPy
Version: 0.0.1.3
Summary: Sintonia do controlador PID utilizando algoritmo de otimização
Home-page: https://github.com/Marcos9971/OptiMultiPy.git
Author: Marcos Antônio Leandro
Author-email: marcos352354@gmail.com
Classifier: Programming Language :: Python :: 3
Classifier: License :: OSI Approved :: MIT License
Classifier: Operating System :: OS Independent
Requires-Python: >=3.6
License-File: licence
